radixulous/__init__.py
radixulous/control.py
radixulous/display.py
radixulous/interactor.py
radixulous/wrecked_elements.py
radixulous/opusmanager/__init__.py
radixulous/opusmanager/errors.py
radixulous/opusmanager/layer_base.py
radixulous/opusmanager/layer_command.py
radixulous/opusmanager/layer_cursor.py
radixulous/opusmanager/layer_flag.py
radixulous/opusmanager/layer_history.py
radixulous/opusmanager/layer_playback.py
radixulous/opusmanager/mgrouping.py
radixulous/opusmanager/midimitter.py
radixulous/opusmanager/structures.py
src/__init__.py
src/control.py
src/display.py
src/interactor.py
src/wrecked_elements.py
src/opusmanager/__init__.py
src/opusmanager/errors.py
src/opusmanager/layer_base.py
src/opusmanager/layer_command.py
src/opusmanager/layer_cursor.py
src/opusmanager/layer_flag.py
src/opusmanager/layer_history.py
src/opusmanager/layer_playback.py
src/opusmanager/mgrouping.py
src/opusmanager/midimitter.py
src/opusmanager/structures.py
radixulous-0.0.3.dist-info/LICENSE
radixulous-0.0.3.dist-info/METADATA
radixulous-0.0.3.dist-info/WHEEL
radixulous-0.0.3.dist-info/entry_points.txt
radixulous-0.0.3.dist-info/top_level.txt
radixulous-0.0.3.dist-info/RECORD
